ezllmaw/__init__.py
ezllmaw/_agent.py
ezllmaw/agent.py
ezllmaw/program.py
ezllmaw/lm/__init__.py
ezllmaw/lm/_deprecated.py
ezllmaw/lm/base_lm.py
ezllmaw/lm/ollama/__init__.py
ezllmaw/lm/ollama/chat_lm.py
ezllmaw/lm/ollama/embedding_model.py
ezllmaw/lm/ollama/gen_lm.py
ezllmaw/lm/ollama/reranker.py
ezllmaw/tools/__init__.py
ezllmaw/tools/tool_calling.py
ezllmaw/tools/tools.py
ezllmaw/utils/__init__.py
ezllmaw/utils/debug.py
ezllmaw/utils/format_instructions.py
ezllmaw/utils/parser.py
ezllmaw/utils/utils.py
ezllmaw-0.0.27.dist-info/LICENSE
ezllmaw-0.0.27.dist-info/METADATA
ezllmaw-0.0.27.dist-info/WHEEL
ezllmaw-0.0.27.dist-info/top_level.txt
ezllmaw-0.0.27.dist-info/RECORD
