Metadata-Version: 2.1
Name: ezllmaw
Version: 0.0.27
Summary: Easy LLM-Agentic Workflow
Home-page: https://github.com/datanooblol/ezllmaw
Author: data.noob.lol
License: MIT
License-File: LICENSE
